pocketbase/__init__.py
pocketbase/client.py
pocketbase/errors.py
pocketbase/models/__init__.py
pocketbase/models/admin.py
pocketbase/models/backups.py
pocketbase/models/collection.py
pocketbase/models/external_auth.py
pocketbase/models/file_upload.py
pocketbase/models/log_request.py
pocketbase/models/record.py
pocketbase/models/utils/__init__.py
pocketbase/models/utils/base_model.py
pocketbase/models/utils/list_result.py
pocketbase/models/utils/schema_field.py
pocketbase/py.typed
pocketbase/services/__init__.py
pocketbase/services/admin_service.py
pocketbase/services/backups_service.py
pocketbase/services/collection_service.py
pocketbase/services/files_service.py
pocketbase/services/health_service.py
pocketbase/services/log_service.py
pocketbase/services/realtime_service.py
pocketbase/services/record_service.py
pocketbase/services/settings_service.py
pocketbase/services/utils/__init__.py
pocketbase/services/utils/base_service.py
pocketbase/services/utils/crud_service.py
pocketbase/services/utils/sse.py
pocketbase/stores/__init__.py
pocketbase/stores/base_auth_store.py
pocketbase/stores/local_auth_store.py
pocketbase/utils.py
pocketbase-0.14.0.dist-info/LICENCE.txt
pocketbase-0.14.0.dist-info/METADATA
pocketbase-0.14.0.dist-info/WHEEL
pocketbase-0.14.0.dist-info/RECORD
