Metadata-Version: 2.1
Name: pocketbase
Version: 0.14.0
Summary: PocketBase SDK for python.
Home-page: https://github.com/vaphes/pocketbase
License: MIT
Keywords: pocketbase,sdk
Author: Vithor Jaeger
Author-email: vaphes@gmail.com
Requires-Python: >=3.9
Classifier: Intended Audience :: Developers
Classifier: License :: OSI Approved :: MIT License
Classifier: Operating System :: OS Independent
Classifier: Programming Language :: Python :: 3
Classifier: Programming Language :: Python :: 3.9
Classifier: Programming Language :: Python :: 3.10
Classifier: Programming Language :: Python :: 3.11
Classifier: Programming Language :: Python :: 3.12
Classifier: Programming Language :: Python :: 3.13
Classifier: Programming Language :: Python :: 3 :: Only
Requires-Dist: httpx (>=0.27.2)
Project-URL: Repository, https://github.com/vaphes/pocketbase
